WeiXueyuanLinuxJiaochengFix1/README.md
WeiXueyuanLinuxJiaochengFix1/__init__.py
WeiXueyuanLinuxJiaochengFix1/__main__.py
WeiXueyuanLinuxJiaochengFix1/file.epub
WeiXueyuanLinuxJiaochengFix1/index.html
WeiXueyuanLinuxJiaochengFix1/css/__init__.py
WeiXueyuanLinuxJiaochengFix1/css/annotations.css
WeiXueyuanLinuxJiaochengFix1/css/main.css
WeiXueyuanLinuxJiaochengFix1/css/normalize.css
WeiXueyuanLinuxJiaochengFix1/css/popup.css
WeiXueyuanLinuxJiaochengFix1/font/__init__.py
WeiXueyuanLinuxJiaochengFix1/font/fontello.eot
WeiXueyuanLinuxJiaochengFix1/font/fontello.svg
WeiXueyuanLinuxJiaochengFix1/font/fontello.ttf
WeiXueyuanLinuxJiaochengFix1/font/fontello.woff
WeiXueyuanLinuxJiaochengFix1/img/__init__.py
WeiXueyuanLinuxJiaochengFix1/img/annotator-glyph-sprite.png
WeiXueyuanLinuxJiaochengFix1/img/annotator-icon-sprite.png
WeiXueyuanLinuxJiaochengFix1/img/apple-touch-icon.png
WeiXueyuanLinuxJiaochengFix1/img/cancelfullscreen.png
WeiXueyuanLinuxJiaochengFix1/img/close.png
WeiXueyuanLinuxJiaochengFix1/img/fullscreen.png
WeiXueyuanLinuxJiaochengFix1/img/loader.gif
WeiXueyuanLinuxJiaochengFix1/img/menu-icon.png
WeiXueyuanLinuxJiaochengFix1/img/save.png
WeiXueyuanLinuxJiaochengFix1/img/saved.png
WeiXueyuanLinuxJiaochengFix1/img/settings-s.png
WeiXueyuanLinuxJiaochengFix1/img/settings.png
WeiXueyuanLinuxJiaochengFix1/img/star.png
WeiXueyuanLinuxJiaochengFix1/js/__init__.py
WeiXueyuanLinuxJiaochengFix1/js/epub.js
WeiXueyuanLinuxJiaochengFix1/js/epub.min.js
WeiXueyuanLinuxJiaochengFix1/js/epub.min.map
WeiXueyuanLinuxJiaochengFix1/js/hooks.min.js
WeiXueyuanLinuxJiaochengFix1/js/hooks.min.map
WeiXueyuanLinuxJiaochengFix1/js/reader.js
WeiXueyuanLinuxJiaochengFix1/js/reader.js.map
WeiXueyuanLinuxJiaochengFix1/js/reader.min.js
WeiXueyuanLinuxJiaochengFix1/js/reader.min.map
WeiXueyuanLinuxJiaochengFix1/js/hooks/__init__.py
WeiXueyuanLinuxJiaochengFix1/js/hooks/extensions/__init__.py
WeiXueyuanLinuxJiaochengFix1/js/hooks/extensions/highlight.js
wei_xueyuan_linux_jiaocheng_fix1-2025.3.25.1.dist-info/METADATA
wei_xueyuan_linux_jiaocheng_fix1-2025.3.25.1.dist-info/WHEEL
wei_xueyuan_linux_jiaocheng_fix1-2025.3.25.1.dist-info/entry_points.txt
wei_xueyuan_linux_jiaocheng_fix1-2025.3.25.1.dist-info/top_level.txt
wei_xueyuan_linux_jiaocheng_fix1-2025.3.25.1.dist-info/RECORD
